pts_ce_control/__init__.py
pts_ce_control/__main__.py
pts_ce_control/cell_emulator.py
pts_ce_control/cellemulator.dbc
pts_ce_control/cellemulator_new.dbc
pts_ce_control-0.0.18.dist-info/METADATA
pts_ce_control-0.0.18.dist-info/WHEEL
pts_ce_control-0.0.18.dist-info/entry_points.txt
pts_ce_control-0.0.18.dist-info/top_level.txt
pts_ce_control-0.0.18.dist-info/RECORD
