Metadata-Version: 2.1
Name: pts-ce-control
Version: 0.0.18
Summary: Controls the PTS Cell Emulator
Home-page: https://gitlab.com/julianpass/cell-emulator-control-app
Author: Pass Testing Solutions GmbH
Author-email: info@pass-testing.de
License: MIT
Platform: UNKNOWN
Classifier: License :: OSI Approved :: MIT License
Classifier: Programming Language :: Python :: 3
Classifier: Programming Language :: Python :: 3.9
Requires-Dist: python-can (>=4.0.0)
Requires-Dist: dash (==2.5.1)
Requires-Dist: cantools (>=37.0.7)
Requires-Dist: tabulate (==0.8.10)
Requires-Dist: uptime (==3.0.1)
